deepdata/__init__.py
deepdata/cifar.py
deepdata/data_loader.py
deepdata/dataset.py
deepdata/mnist.py
deepdata/transforms.py
deepdata/urls.py
deepdata/utils.py
deepdata/mirror/__init__.py
deepdata/mirror/zh.py
deepdata-0.2.1.dist-info/LICENSE
deepdata-0.2.1.dist-info/METADATA
deepdata-0.2.1.dist-info/WHEEL
deepdata-0.2.1.dist-info/top_level.txt
deepdata-0.2.1.dist-info/RECORD
